adaptive_cards_python/Py.typed
adaptive_cards_python/__init__.py
adaptive_cards_python/_version.pyi
adaptive_cards_python/msteams.py
adaptive_cards_python/validation.py
adaptive_cards_python/adaptive_card/Action.py
adaptive_cards_python/adaptive_card/AdaptiveCard.py
adaptive_cards_python/adaptive_card/BackgroundImage.py
adaptive_cards_python/adaptive_card/Element.py
adaptive_cards_python/adaptive_card/Extendable.py
adaptive_cards_python/adaptive_card/__init__.py
adaptive_cards_python/adaptive_card/adaptive-card.json
adaptive_cards_python/adaptive_card/config.py
adaptive_cards_python-0.1.11.dist-info/METADATA
adaptive_cards_python-0.1.11.dist-info/WHEEL
adaptive_cards_python-0.1.11.dist-info/licenses/LICENSE
adaptive_cards_python-0.1.11.dist-info/RECORD
