Metadata-Version: 2.4
Name: adaptive-cards-python
Version: 0.1.11
Summary: Fully typed & validated Adaptive Card implementation using Pydantic.
Project-URL: Homepage, https://github.com/emirkmo/adaptive-cards-python.git
Project-URL: Repository, https://github.com/emirkmo/adaptive-cards-python.git
Project-URL: Issues, https://github.com/emirkmo/adaptive-cards-python/issues
Project-URL: Changelog, https://github.com/emirkmo/adaptive-cards-python/releases
Author-email: Emir Karamehmetoglu <emirk@axis.com>
License-Expression: MIT
License-File: LICENSE
Keywords: adaptive-cards,datamodel-code-gen,jsonschema,microsoft-teams,pydantic,webhook
Classifier: Development Status :: 4 - Beta
Classifier: Framework :: Pydantic
Classifier: Intended Audience :: Developers
Classifier: License :: OSI Approved :: MIT License
Classifier: Natural Language :: English
Classifier: Operating System :: OS Independent
Classifier: Programming Language :: Python :: 3
Classifier: Programming Language :: Python :: 3 :: Only
Classifier: Programming Language :: Python :: 3.12
Classifier: Programming Language :: Python :: 3.13
Classifier: Programming Language :: Python :: 3.14
Classifier: Topic :: File Formats :: JSON :: JSON Schema
Classifier: Topic :: Software Development :: Libraries
Classifier: Topic :: Software Development :: Libraries :: Python Modules
Classifier: Typing :: Typed
Requires-Python: >=3.12
Requires-Dist: jsonschema>=4.0.0
Requires-Dist: orjson>=3.10.18
Requires-Dist: pydantic-extra-types>=2.10.4
Requires-Dist: pydantic>=2.11.4
Requires-Dist: requests>=2.0.0
